lmao/__init__.py
lmao/factory.py
lmao/adapters/__init__.py
lmao/adapters/base.py
lmao/adapters/chatbot.py
lmao/adapters/classification.py
lmao/adapters/client_mixins.py
lmao/adapters/fermi.py
lmao/clients/__init__.py
lmao/clients/anthropic.py
lmao/clients/base.py
lmao/clients/cohere.py
lmao/clients/openai.py
lmao/clients/utils.py
lmao/clients/schemas/__init__.py
lmao/clients/schemas/anthropic.py
lmao/clients/schemas/base.py
lmao/clients/schemas/cohere.py
lmao/clients/schemas/openai.py
lmao/orchestrators/__init__.py
lmao/orchestrators/base.py
lmao/prompters/__init__.py
lmao/prompters/base.py
lmao/prompters/classification.py
lmao/prompters/fermi.py
lmao/tasks/__init__.py
lmao/tasks/base.py
lmao/tasks/chatbot.py
lmao/tasks/classification.py
lmao/tasks/fermi.py
lmao_nlp-0.0.1.dist-info/LICENSE
lmao_nlp-0.0.1.dist-info/METADATA
lmao_nlp-0.0.1.dist-info/WHEEL
lmao_nlp-0.0.1.dist-info/top_level.txt
lmao_nlp-0.0.1.dist-info/RECORD
